tbxtools/__init__.py
tbxtools-0.1.0.dist-info/METADATA
tbxtools-0.1.0.dist-info/WHEEL
tbxtools-0.1.0.dist-info/top_level.txt
tbxtools-0.1.0.dist-info/RECORD
